Workbook

Sheet Cover
A2: FINANCIAL STATEMENT ANALYSIS
A3: Infosys Limited (NSE: INFY)
A4: FY2023 | FY2024 | FY2025
A6: Prepared by: Tharineesh M
A7: B.Com | SAP S/4HANA Certified Associate — Financial Accounting
A9: Date: Apr 2026
A11: Contents:
A12: 1. Raw_Data — Source financial figures extracted from annual reports
A13: 2. Ratios_Calc — 11 ratios calculated across 3 years
A14: 3. Trend_Analysis — Visual charts for each ratio category
A15: 4. Insights — Business interpretation and key observations
A16: 5. Executive_Summary — One-page summary of findings
A17: 6. Source_Notes — Data sources, page references, and assumptions

Sheet Raw_Data
A1: Item | B1: FY2023 | C1: FY2024 | D1: FY2025 | E1: Unit
A2: BALANCE SHEET DATA
A3: Current Assets | B3: 52082 | C3: 70952 | D3: 77168 | E3: ₹ Crores
A4: Inventories | B4: 0 | C4: 0 | D4: 0 | E4: ₹ Crores
A5: Cash and Cash Equivalents | B5: 6534 | C5: 8191 | D5: 14265 | E5: ₹ Crores
A6: Total Assets | B6: 101337 | C6: 114950 | D6: 124936 | E6: ₹ Crores
A7: Current Liabilities | B7: 27442 | C7: 27086 | D7: 31762 | E7: ₹ Crores
A8: Total Debt (Borrowings) | B8: 0 | C8: 0 | D8: 0 | E8: ₹ Crores
A9: Total Equity | B9: 67745 | C9: 81176 | D9: 87332 | E9: ₹ Crores
A11: P&L DATA
A12: Revenue from Operations | B12: 124014 | C12: 128933 | D12: 136592 | E12: ₹ Crores
A13: Gross Profit | B13: 42154 | C13: 45156 | D13: 49773 | E13: ₹ Crores
A14: Operating Profit (EBIT) | B14: 31800 | C14: 36230 | D14: 35662 | E14: ₹ Crores
A15: Finance Costs (Interest) | B15: 157 | C15: 277 | D15: 221 | E15: ₹ Crores
A16: Net Profit | B16: 23268 | C16: 27234 | D16: 25568 | E16: ₹ Crores
A18: Source: Infosys Annual Reports FY2023–FY2025, Standalone Financial Statements

Sheet Ratios_Calc
A1: Ratio | B1: Formula | C1: FY2023 | D1: FY2024 | E1: FY2025 | F1: Trend (FY23→25) | G1: Interpretation | H1: FY23→24 Change | I1: FY24→25 Change
A3: SECTION A — LIQUIDITY RATIOS
A4: Current Ratio | B4: Current Assets / Current Liabilities | C4: =Raw_Data!B3/Raw_Data!B7 -> 1.8978937 | D4: =Raw_Data!C3/Raw_Data!C7 -> 2.6195082 | E4: =Raw_Data!D3/Raw_Data!D7 -> 2.4295699 | F4: =IF(E4>C4,"Improving","Declining") -> Improving | G4: Measures ability to meet short-term obligations. Healthy if above 1.5. | H4: =(D4-C4)/C4 -> 0.3802186 | I4: =(E4-D4)/D4 -> -0.072509147
A5: Quick Ratio | B5: (Current Assets - Inventories) / Current Liabilities | C5: =(Raw_Data!B3-Raw_Data!B4)/Raw_Data!B7 -> 1.8978937 | D5: =(Raw_Data!C3-Raw_Data!C4)/Raw_Data!C7 -> 2.6195082 | E5: =(Raw_Data!D3-Raw_Data!D4)/Raw_Data!D7 -> 2.4295699 | F5: =IF(E5>C5,"Improving","Declining") -> Improving | G5: Stricter liquidity test excluding inventory. Above 1.0 is healthy. | H5: =(D5-C5)/C5 -> 0.3802186 | I5: =(E5-D5)/D5 -> -0.072509147
A6: Cash Ratio | B6: Cash and Equivalents / Current Liabilities | C6: =Raw_Data!B5/Raw_Data!B7 -> 0.23810218 | D6: =Raw_Data!C5/Raw_Data!C7 -> 0.30240715 | E6: =Raw_Data!D5/Raw_Data!D7 -> 0.44912159 | F6: =IF(E6>C6,"Improving","Declining") -> Improving | G6: Most conservative liquidity measure. Shows immediate payment ability. | H6: =(D6-C6)/C6 -> 0.27007299 | I6: =(E6-D6)/D6 -> 0.48515535
A8: SECTION B — PROFITABILITY RATIOS
A9: Gross Profit Margin | B9: Gross Profit / Revenue | C9: =Raw_Data!B13/Raw_Data!B12 -> 0.33991324 | D9: =Raw_Data!C13/Raw_Data!C12 -> 0.35022841 | E9: =Raw_Data!D13/Raw_Data!D12 -> 0.36439177 | F9: =IF(E9>C9,"Improving","Declining") -> Improving | G9: Shows efficiency in service delivery before overhead. Higher is better. | H9: =(D9-C9)/C9 -> 0.030346502 | I9: =(E9-D9)/D9 -> 0.040440328
A10: Operating Profit Margin | B10: Operating Profit (EBIT) / Revenue | C10: =Raw_Data!B14/Raw_Data!B12 -> 0.25642266 | D10: =Raw_Data!C14/Raw_Data!C12 -> 0.28099866 | E10: =Raw_Data!D14/Raw_Data!D12 -> 0.2610841 | F10: =IF(E10>C10,"Improving","Declining") -> Improving | G10: Shows operational efficiency after all operating expenses. | H10: =(D10-C10)/C10 -> 0.095841748 | I10: =(E10-D10)/D10 -> -0.070870636
A11: Net Profit Margin | B11: Net Profit / Revenue | C11: =Raw_Data!B16/Raw_Data!B12 -> 0.18762398 | D11: =Raw_Data!C16/Raw_Data!C12 -> 0.21122599 | E11: =Raw_Data!D16/Raw_Data!D12 -> 0.18718519 | F11: =IF(E11>C11,"Improving","Declining") -> Declining | G11: Final profitability after all costs including tax and interest. | H11: =(D11-C11)/C11 -> 0.1257942 | I11: =(E11-D11)/D11 -> -0.1138155
A12: Return on Assets (ROA) | B12: Net Profit / Total Assets | C12: =Raw_Data!B16/Raw_Data!B6 -> 0.22961011 | D12: =Raw_Data!C16/Raw_Data!C6 -> 0.2369204 | E12: =Raw_Data!D16/Raw_Data!D6 -> 0.20464878 | F12: =IF(E12>C12,"Improving","Declining") -> Declining | G12: How efficiently total assets generate profit. Higher is better. | H12: =(D12-C12)/C12 -> 0.031837828 | I12: =(E12-D12)/D12 -> -0.13621292
A13: Return on Equity (ROE) | B13: Net Profit / Total Equity | C13: =Raw_Data!B16/Raw_Data!B9 -> 0.34346446 | D13: =Raw_Data!C16/Raw_Data!C9 -> 0.33549325 | E13: =Raw_Data!D16/Raw_Data!D9 -> 0.29276783 | F13: =IF(E13>C13,"Improving","Declining") -> Declining | G13: Returns generated for shareholders. Key metric for investors. | H13: =(D13-C13)/C13 -> -0.023208262 | I13: =(E13-D13)/D13 -> -0.12735106
A15: SECTION C — LEVERAGE RATIOS
A16: Debt to Equity | B16: Total Debt / Total Equity | C16: =IF(Raw_Data!B8=0,0,Raw_Data!B8/Raw_Data!B9) -> 0 | D16: =IF(Raw_Data!C8=0,0,Raw_Data!C8/Raw_Data!C9) -> 0 | E16: =IF(Raw_Data!D8=0,0,Raw_Data!D8/Raw_Data!D9) -> 0 | F16: =IF(E16<C16,"Improving",IF(E16=C16,"Stable","Rising")) -> Stable | G16: Lower D/E means less financial risk. Below 1.0 is conservative. Infosys = 0 (debt-free). | H16: =IF(C16=0,0,(D16-C16)/C16) -> 0 | I16: =IF(D16=0,0,(E16-D16)/D16) -> 0
A17: Debt Ratio | B17: Total Debt / Total Assets | C17: =IF(Raw_Data!B8=0,0,Raw_Data!B8/Raw_Data!B6) -> 0 | D17: =IF(Raw_Data!C8=0,0,Raw_Data!C8/Raw_Data!C6) -> 0 | E17: =IF(Raw_Data!D8=0,0,Raw_Data!D8/Raw_Data!D6) -> 0 | F17: =IF(E17<C17,"Improving",IF(E17=C17,"Stable","Rising")) -> Stable | G17: Proportion of assets financed by debt. 0.0 = fully equity-financed. | H17: =IF(C17=0,0,(D17-C17)/C17) -> 0 | I17: =IF(D17=0,0,(E17-D17)/D17) -> 0
A18: Interest Coverage Ratio | B18: EBIT / Finance Costs (ICR) | C18: =IF(Raw_Data!B15=0,"N/A",Raw_Data!B14/Raw_Data!B15) -> 202.54777 | D18: =IF(Raw_Data!C15=0,"N/A",Raw_Data!C14/Raw_Data!C15) -> 130.79422 | E18: =IF(Raw_Data!D15=0,"N/A",Raw_Data!D14/Raw_Data!D15) -> 161.36652 | F18: =IF(ISNUMBER(E18),IF(E18>C18,"Improving","Declining"),"See Note") -> Declining | G18: Finance costs = lease interest only (no traditional debt). Above 3x is healthy. | H18: =IF(OR(NOT(ISNUMBER(C18)),NOT(ISNUMBER(D18))),"-",(D18-C18)/C18) -> -0.35425493 | I18: =IF(OR(NOT(ISNUMBER(D18)),NOT(ISNUMBER(E18))),"-",(E18-D18)/D18) -> 0.23374344

Sheet Trend_Analysis
K52: FY2023 | L52: FY2024 | M52: FY2025
J53: Current Ratio | K53: =Ratios_Calc!C4 -> 1.8978937 | L53: =Ratios_Calc!D4 -> 2.6195082 | M53: =Ratios_Calc!E4 -> 2.4295699
J54: Quick Ratio | K54: =Ratios_Calc!C5 -> 1.8978937 | L54: =Ratios_Calc!D5 -> 2.6195082 | M54: =Ratios_Calc!E5 -> 2.4295699
J55: Cash Ratio | K55: =Ratios_Calc!C6 -> 0.23810218 | L55: =Ratios_Calc!D6 -> 0.30240715 | M55: =Ratios_Calc!E6 -> 0.44912159
K58: FY2023 | L58: FY2024 | M58: FY2025
J59: Gross Profit Margin | K59: =Ratios_Calc!C9 -> 0.33991324 | L59: =Ratios_Calc!D9 -> 0.35022841 | M59: =Ratios_Calc!E9 -> 0.36439177
J60: Operating Profit Margin | K60: =Ratios_Calc!C10 -> 0.25642266 | L60: =Ratios_Calc!D10 -> 0.28099866 | M60: =Ratios_Calc!E10 -> 0.2610841
J61: Net Profit Margin | K61: =Ratios_Calc!C11 -> 0.18762398 | L61: =Ratios_Calc!D11 -> 0.21122599 | M61: =Ratios_Calc!E11 -> 0.18718519
K64: FY2023 | L64: FY2024 | M64: FY2025
J65: Debt to Equity | K65: =Ratios_Calc!C16 -> 0 | L65: =Ratios_Calc!D16 -> 0 | M65: =Ratios_Calc!E16 -> 0
J66: Debt Ratio | K66: =Ratios_Calc!C17 -> 0 | L66: =Ratios_Calc!D17 -> 0 | M66: =Ratios_Calc!E17 -> 0

Sheet Insights
A1: FINANCIAL INSIGHTS — INFOSYS LIMITED (FY2023–FY2025)
A3: LIQUIDITY INSIGHTS
A4: 1. | B4: Infosys maintained a strong Current Ratio above 1.90x across all 3 years, improving significantly from 1.90x in FY2023 to 2.62x in FY2024, before moderating to 2.43x in FY2025. This reflects consistently strong ability to meet short-term obligations without liquidity stress.
A5: 2. | B5: The Quick Ratio is identical to the Current Ratio in all three years because Infosys, being an IT services company, carries near-zero inventory. This means all current assets are inherently liquid — a structural advantage of the services model.
A6: 3. | B6: Cash and Cash Equivalents nearly doubled from ₹6,534 Cr in FY2023 to ₹14,265 Cr in FY2025, reflecting strong free cash flow generation. The Cash Ratio improved from 0.24x to 0.45x, indicating significantly enhanced immediate payment capacity over the period.
A8: PROFITABILITY INSIGHTS
A9: 4. | B9: Gross Profit Margin expanded consistently from 34.0% in FY2023 to 36.4% in FY2025, indicating improving efficiency in service delivery. Revenue grew at a faster pace than the combined employee and sub-contractor cost base, reflecting pricing power and operational discipline.
A10: 5. | B10: Operating Profit Margin peaked at 28.1% in FY2024 before declining to 26.1% in FY2025. The FY2025 compression was driven by a surge in software package costs (₹6,891 Cr in FY2024 to ₹9,617 Cr in FY2025), reflecting higher AI/technology infrastructure investment.
A11: 6. | B11: The gap between Gross Margin (36.4%) and Net Margin (18.7%) in FY2025 is approximately 17.7%, representing SG&A, depreciation, tax, and other overhead. This gap widened from FY2024's ~14.0%, indicating that below-the-gross-profit costs grew disproportionately in FY2025.
A12: 7. | B12: Return on Equity declined from 34.3% in FY2023 to 29.3% in FY2025, as equity grew faster than net profit. ROA also moderated from 23.0% to 20.5%. Both metrics remain strong in absolute terms and are above typical IT sector benchmarks.
A14: LEVERAGE INSIGHTS
A15: 7. | B15: Infosys operates with a completely debt-free capital structure across all three years — the Debt-to-Equity ratio is 0.0x and the Debt Ratio is 0.0 in FY2023, FY2024, and FY2025. The company relies entirely on internal accruals and equity for growth financing. Finance costs present in the P&L arise solely from lease liabilities (Ind AS 116), not traditional borrowings.
A17: OVERALL BUSINESS CONCLUSION
A18: Infosys demonstrated strong and broadly stable financial health between FY2023 and FY2025. Liquidity improved significantly — the Current Ratio rose from 1.90x to 2.43x and cash holdings nearly doubled — supported by robust free cash flow generation. Gross profitability improved consistently as the company managed its core cost base effectively, but operating and net margins faced pressure in FY2025 from rising software and technology infrastructure spend, partly related to AI capability investment. The debt-free balance sheet confirms minimal financial risk, and returns to shareholders remain strong despite a natural moderation as the equity base expanded through retained earnings. Overall, the company maintains solid financial fundamentals suited for long-term stable growth.

Sheet Executive_Summary
A1: EXECUTIVE SUMMARY
A2: Financial Statement Analysis — Infosys Limited
A3: Period: FY2023 to FY2025 | Prepared by: Tharineesh M
A4: ──────────────────────────────────────────────────────────────────────
A5: OBJECTIVE
A6: To analyze Infosys Limited's 3-year standalone financial performance using key accounting ratios across liquidity, profitability, and leverage dimensions.
A7: ──────────────────────────────────────────────────────────────────────
A8: KEY RATIOS SNAPSHOT (FY2025)
A9: Liquidity: Current Ratio | B9: =Ratios_Calc!E4&"x" -> 2.42956992632706x
A10: Liquidity: Quick Ratio | B10: =Ratios_Calc!E5&"x" -> 2.42956992632706x
A11: Profitability: Net Profit Margin | B11: =TEXT(Ratios_Calc!E11,"0.0%") -> 18.7%
A12: Profitability: Return on Equity | B12: =TEXT(Ratios_Calc!E13,"0.0%") -> 29.3%
A13: Leverage: Debt to Equity | B13: =Ratios_Calc!E16&"x" -> 0x
A14: ──────────────────────────────────────────────────────────────────────
A15: KEY FINDINGS
A16: 1. Liquidity Improvement | B16: Current Ratio rose from 1.90x (FY2023) to 2.43x (FY2025), and cash holdings nearly doubled to ₹14,265 Cr, reflecting strong free cash flow generation.
A17: 2. Gross Margin Expansion | B17: Gross Profit Margin improved from 34.0% to 36.4% over 3 years, indicating improving service delivery efficiency and cost discipline on core operations.
A18: 3. Net Margin Pressure in FY2025 | B18: Net Profit Margin declined from 21.1% (FY2024) to 18.7% (FY2025) as software package and AI infrastructure costs surged, compressing the operating line.
A19: 4. Strong Shareholder Returns | B19: Return on Equity remained above 29% in FY2025 despite pressure, and ROA of 20.5% reflects efficient asset utilization across the 3-year period.
A20: 5. Debt-Free Capital Structure | B20: Zero borrowings across all 3 years — Infosys is entirely equity-financed, confirming minimal financial risk and conservative capital management.
A21: ──────────────────────────────────────────────────────────────────────
A22: CONCLUSION
A23: Infosys demonstrated strong financial health between FY2023 and FY2025. Liquidity improved substantially, supported by robust cash generation, while gross profitability expanded consistently. Net margins faced moderate pressure in FY2025 from rising technology and AI investment costs — a strategic trade-off rather than a structural weakness. The debt-free balance sheet and consistently strong ROE confirm that Infosys remains a financially sound, low-risk company suited to long-term stable growth. For anyone working with or investing in Infosys, the key watchpoint for FY2026 is whether the increased technology investment begins to translate into margin recovery.
A24: ──────────────────────────────────────────────────────────────────────
A25: Data Source: Infosys Annual Reports FY2023, FY2024, FY2025 (Standalone Financial Statements)
A26: Tools Used: Microsoft Excel — IF, cross-sheet references, percentage change formulas, Line/Column/Bar charts

Sheet Source_Notes
A1: # | B1: Data Item | C1: Source Document | D1: Page No. | E1: URL
A2: 1 | B2: FY2025 Balance Sheet | C2: Infosys Annual Report 2024-25, Standalone FS | D2: 222 | E2: https://www.infosys.com/investors/reports-filings/annual-report/annual-reports.html
A3: 2 | B3: FY2025 P&L Statement | C3: Infosys Annual Report 2024-25, Standalone FS | D3: 223 | E3: https://www.infosys.com/investors/reports-filings/annual-report/annual-reports.html
A4: 3 | B4: FY2024 Balance Sheet | C4: Infosys Annual Report 2023-24, Standalone FS | D4: 217 | E4: https://www.infosys.com/investors/reports-filings/annual-report/annual-reports.html
A5: 4 | B5: FY2024 P&L Statement | C5: Infosys Annual Report 2023-24, Standalone FS | D5: 218 | E5: https://www.infosys.com/investors/reports-filings/annual-report/annual-reports.html
A6: 5 | B6: FY2023 Balance Sheet | C6: Infosys Annual Report 2022-23, Standalone FS | D6: 219 | E6: https://www.infosys.com/investors/reports-filings/annual-report/annual-reports.html
A7: 6 | B7: FY2023 P&L Statement | C7: Infosys Annual Report 2022-23, Standalone FS | D7: 221 | E7: https://www.infosys.com/investors/reports-filings/annual-report/annual-reports.html
A10: ASSUMPTIONS
A11: 1. Gross Profit was derived as [Revenue from Operations − Employee Benefit Expenses − Cost of Technical Sub-Contractors] because Infosys does not separately report Cost of Goods Sold. This approach is documented in all three annual reports under the function-wise P&L classification (Notes to Accounts).
A12: 2. Total Debt (Borrowings) is NIL for all three years. Infosys carries no Short-term or Long-term bank borrowings on its standalone balance sheet. Finance Costs reported in the P&L relate exclusively to lease liabilities under Ind AS 116.
A13: 3. All figures are in Indian Rupees (₹ Crores) as reported in the respective Standalone Financial Statements. No currency conversion has been applied.
A14: 4. EBIT (Operating Profit) has been derived as Profit before Tax + Finance Costs, consistent with the definition of Profit before Finance Costs and Tax.
A15: 5. Inventories are NIL for all three years, as expected for an IT services company. Current Ratio and Quick Ratio are therefore identical.
A16: 6. FY2023 figures were cross-verified between the FY2022-23 Annual Report (primary) and the FY2023-24 Annual Report (comparative year). Both sources confirm identical values.
